django_twitch_auth/__init__.py
django_twitch_auth/authbackends.py
django_twitch_auth/exceptions.py
django_twitch_auth/middlewares.py
django_twitch_auth/settings.py
django_twitch_auth/urls.py
django_twitch_auth/views.py
django_twitch_auth-0.1.0.dist-info/LICENSE
django_twitch_auth-0.1.0.dist-info/METADATA
django_twitch_auth-0.1.0.dist-info/WHEEL
django_twitch_auth-0.1.0.dist-info/top_level.txt
django_twitch_auth-0.1.0.dist-info/RECORD
