Metadata-Version: 2.1
Name: django-twitch-auth
Version: 0.1.0
Summary: Django Authetication with Twitch.
Home-page: https://github.com/leonextlevel/django-twitch-auth
Author: LeoNextLevel
Author-email: leonextlevel@gmail.com
License: UNKNOWN
Project-URL: Bug Tracker, https://github.com/leonextlevel/django-twitch-auth/issues
Platform: UNKNOWN
Classifier: Programming Language :: Python :: 3
Classifier: License :: OSI Approved :: MIT License
Classifier: Operating System :: OS Independent
Requires-Python: >=3.6
License-File: LICENSE
